<?xml version="1.0" encoding="utf-8" ?><dwsync><file name=".DS_Store" server="ftp.aaronstrickland.co.uk" local="3496177138" remote="3499815720" Dst="-1" /><file name="breitling-brand-logo1.png" server="ftp.aaronstrickland.co.uk" local="3494766292" remote="3499815720" Dst="-1" /><file name="Cartier-brand-logo1.png" server="ftp.aaronstrickland.co.uk" local="3494766379" remote="3499815720" Dst="-1" /><file name="Chopard-Brand-Image1.png" server="ftp.aaronstrickland.co.uk" local="3494766374" remote="3499815720" Dst="-1" /><file name="hublot.png" server="ftp.aaronstrickland.co.uk" local="3494766313" remote="3499815720" Dst="-1" /><file name="franck-muller-logo copy.png" server="ftp.aaronstrickland.co.uk" local="3494766741" remote="3499815780" Dst="-1" /><file name="Mondaine-Logo.png" server="ftp.aaronstrickland.co.uk" local="3494766236" remote="3499815780" Dst="-1" /><file name="Omega-Brand-Logo1.png" server="ftp.aaronstrickland.co.uk" local="3494763295" remote="3499815780" Dst="-1" /><file name="Rolex-21.png" server="ftp.aaronstrickland.co.uk" local="3494766397" remote="3499815780" Dst="-1" /><file name="TagHeuer-Brand-Logo1.png" server="ftp.aaronstrickland.co.uk" local="3494766345" remote="3499815780" Dst="-1" /><file name="wos-logo-highres-alt.png" server="ftp.aaronstrickland.co.uk" local="3494772481" remote="3499815780" Dst="-1" /></dwsync>